nicegui_highcharts/__init__.py
nicegui_highcharts/dist/accessibility-DXYezIHS.js
nicegui_highcharts/dist/accessibility-DXYezIHS.js.map
nicegui_highcharts/dist/annotations-CYEHi9wR.js
nicegui_highcharts/dist/annotations-CYEHi9wR.js.map
nicegui_highcharts/dist/annotations-advanced-BoLYldCC.js
nicegui_highcharts/dist/annotations-advanced-BoLYldCC.js.map
nicegui_highcharts/dist/arc-diagram-nYU25n0C.js
nicegui_highcharts/dist/arc-diagram-nYU25n0C.js.map
nicegui_highcharts/dist/arrow-symbols-Bquz8MdI.js
nicegui_highcharts/dist/arrow-symbols-Bquz8MdI.js.map
nicegui_highcharts/dist/boost-Dp6O-S3K.js
nicegui_highcharts/dist/boost-Dp6O-S3K.js.map
nicegui_highcharts/dist/boost-canvas-CCtXUj2f.js
nicegui_highcharts/dist/boost-canvas-CCtXUj2f.js.map
nicegui_highcharts/dist/broken-axis-oBRjh2uu.js
nicegui_highcharts/dist/broken-axis-oBRjh2uu.js.map
nicegui_highcharts/dist/bullet-BZCcyGbt.js
nicegui_highcharts/dist/bullet-BZCcyGbt.js.map
nicegui_highcharts/dist/coloraxis-DXmE9jlM.js
nicegui_highcharts/dist/coloraxis-DXmE9jlM.js.map
nicegui_highcharts/dist/current-date-indicator-CL-Hjmq1.js
nicegui_highcharts/dist/current-date-indicator-CL-Hjmq1.js.map
nicegui_highcharts/dist/cylinder-e-HaAtPz.js
nicegui_highcharts/dist/cylinder-e-HaAtPz.js.map
nicegui_highcharts/dist/data-DfUgfT8Q.js
nicegui_highcharts/dist/data-DfUgfT8Q.js.map
nicegui_highcharts/dist/data-tools-DQi0qw-m.js
nicegui_highcharts/dist/data-tools-DQi0qw-m.js.map
nicegui_highcharts/dist/datagrouping-DM3T1rXn.js
nicegui_highcharts/dist/datagrouping-DM3T1rXn.js.map
nicegui_highcharts/dist/debugger-DvNHogyR.js
nicegui_highcharts/dist/debugger-DvNHogyR.js.map
nicegui_highcharts/dist/dependency-wheel-DelQhIt0.js
nicegui_highcharts/dist/dependency-wheel-DelQhIt0.js.map
nicegui_highcharts/dist/dotplot-Dn3rvcYV.js
nicegui_highcharts/dist/dotplot-Dn3rvcYV.js.map
nicegui_highcharts/dist/drag-panes-DDnXSwLH.js
nicegui_highcharts/dist/drag-panes-DDnXSwLH.js.map
nicegui_highcharts/dist/draggable-points-CuV-68GY.js
nicegui_highcharts-3.1.0.dist-info/METADATA
nicegui_highcharts-3.1.0.dist-info/WHEEL
nicegui_highcharts-3.1.0.dist-info/licenses/LICENSE
nicegui_highcharts-3.1.0.dist-info/RECORD
