Metadata-Version: 2.4
Name: nicegui-highcharts
Version: 3.1.0
Summary: Add Highcharts elements to your NiceGUI app.
License: MIT
License-File: LICENSE
Keywords: charts,highcharts,gui,ui,web
Author: Zauberzeug GmbH
Author-email: info@zauberzeug.com
Requires-Python: >=3.9,<4.0
Classifier: License :: OSI Approved :: MIT License
Classifier: Programming Language :: Python :: 3
Classifier: Programming Language :: Python :: 3.9
Classifier: Programming Language :: Python :: 3.10
Classifier: Programming Language :: Python :: 3.11
Classifier: Programming Language :: Python :: 3.12
Classifier: Programming Language :: Python :: 3.13
Classifier: Programming Language :: Python :: 3.14
Requires-Dist: nicegui (>=3.0.0,<4.0.0)
Project-URL: Repository, https://github.com/zauberzeug/nicegui-highcharts
